LICENSE
MANIFEST.in
README.md
README.rst
setup.py
django_2gis_maps/__init__.py
django_2gis_maps/admin.py
django_2gis_maps/fields.py
django_2gis_maps/mixins.py
django_2gis_maps/models.py
django_2gis_maps/widgets.py
django_2gis_maps.egg-info/PKG-INFO
django_2gis_maps.egg-info/SOURCES.txt
django_2gis_maps.egg-info/dependency_links.txt
django_2gis_maps.egg-info/not-zip-safe
django_2gis_maps.egg-info/requires.txt
django_2gis_maps.egg-info/top_level.txt
django_2gis_maps/static/django_2gis_maps/css/adminMap.css
django_2gis_maps/static/django_2gis_maps/css/adminMapMultipleMarkers.css
django_2gis_maps/static/django_2gis_maps/js/addMarkers.js
django_2gis_maps/static/django_2gis_maps/js/adminMap.js
django_2gis_maps/static/django_2gis_maps/js/adminMapMultipleMarkers.js
django_2gis_maps/templates/django_2gis_maps/map/map.html
django_2gis_maps/templates/django_2gis_maps/widgets/map_widget.html
django_2gis_maps/templates/django_2gis_maps/widgets/multiple_markers_widget.html
django_2gis_maps/templatetags/__init__.py
django_2gis_maps/templatetags/doublegis.py
django_2gis_maps/templatetags/__pycache__/__init__.cpython-37.pyc
django_2gis_maps/templatetags/__pycache__/doublegis.cpython-37.pyc
requirements/requirements.txt
requirements/test.txt